LICENSE
README.md
setup.py
xfd/__init__.py
xfd.egg-info/PKG-INFO
xfd.egg-info/SOURCES.txt
xfd.egg-info/dependency_links.txt
xfd.egg-info/requires.txt
xfd.egg-info/top_level.txt